setup.py
dm/__init__.py
dm.zope.notmuchmail.egg-info/PKG-INFO
dm.zope.notmuchmail.egg-info/SOURCES.txt
dm.zope.notmuchmail.egg-info/dependency_links.txt
dm.zope.notmuchmail.egg-info/namespace_packages.txt
dm.zope.notmuchmail.egg-info/not-zip-safe
dm.zope.notmuchmail.egg-info/requires.txt
dm.zope.notmuchmail.egg-info/top_level.txt
dm/zope/__init__.py
dm/zope/notmuchmail/LICENSE.txt
dm/zope/notmuchmail/README.txt
dm/zope/notmuchmail/VERSION.txt
dm/zope/notmuchmail/__init__.py
dm/zope/notmuchmail/interfaces.py
dm/zope/notmuchmail/notmuchmail.py
dm/zope/notmuchmail/user.zcml
dm/zope/notmuchmail/browser/__init__.py
dm/zope/notmuchmail/browser/combined.pt
dm/zope/notmuchmail/browser/configure.zcml
dm/zope/notmuchmail/browser/interfaces.py
dm/zope/notmuchmail/browser/jqui.zcml
dm/zope/notmuchmail/browser/message.pt
dm/zope/notmuchmail/browser/search.py
dm/zope/notmuchmail/browser/thread.pt
dm/zope/notmuchmail/browser/threads.pt
dm/zope/notmuchmail/browser/resources/close.png
dm/zope/notmuchmail/browser/resources/email.css
dm/zope/notmuchmail/browser/resources/jquery-1.11.0.min.js
dm/zope/notmuchmail/browser/resources/jqui.js
dm/zope/notmuchmail/browser/resources/open.png
dm/zope/notmuchmail/browser/standalone/__init__.py
dm/zope/notmuchmail/browser/standalone/configure.zcml
dm/zope/notmuchmail/browser/standalone/form_template.pt
dm/zope/notmuchmail/browser/standalone/template.pt
dm/zope/notmuchmail/browser/standalone/wrap.py