Metadata-Version: 1.1
Name: dm.zope.notmuchmail
Version: 0.1b1
Summary: Zope interface to the email indexer and retriever `notmuch[mail]`
Home-page: http://pypi.python.org/pypi/dm.zope.notmuchmail
Author: Dieter Maurer
Author-email: dieter@handshake.de
License: BSD
Keywords: email retrieval zope notmuchmail notmuch
Platform: UNKNOWN
Classifier: Development Status :: 4 - Beta
Classifier: Intended Audience :: Developers
Classifier: Intended Audience :: System Administrators
Classifier: Intended Audience :: End Users/Desktop
Classifier: License :: OSI Approved :: BSD License
Classifier: Framework :: Zope2
Classifier: Operating System :: OS Independent
Classifier: Programming Language :: Python
Classifier: Topic :: Utilities
Classifier: Topic :: Communications :: Email
